<Properties>
  <MultiItemStartupConfigurations />
  <MonoDevelop.Ide.DebuggingService.Breakpoints>
    <BreakpointStore />
  </MonoDevelop.Ide.DebuggingService.Breakpoints>
  <MonoDevelop.Ide.Workbench ActiveDocument="Psychology/main/Personality/PersonalityNode.cs">
    <Files>
      <File FileName="Psychology/Main/Personality/PersonalityNode.cs" Line="39" Column="112" IsPinned="True" />
    </Files>
    <Pads>
      <Pad Id="ProjectPad">
        <State name="__root__">
          <Node name="PsychologyUnofficialMac" expanded="True">
            <Node name="PsychologyMac" expanded="True">
              <Node name="References" expanded="True" />
              <Node name="Common" expanded="True">
                <Node name="Defs" expanded="True">
                  <Node name="PersonalityDefs" expanded="True" />
                </Node>
              </Node>
              <Node name="Defs" expanded="True" />
              <Node name="Harmony" expanded="True" />
              <Node name="Main" expanded="True">
                <Node name="Conversations" expanded="True" />
                <Node name="Elections" expanded="True" />
                <Node name="Personality" expanded="True">
                  <Node name="PersonalityNode.cs" selected="True" />
                </Node>
                <Node name="Recruiting" expanded="True" />
                <Node name="ThoughtWorkers" expanded="True" />
              </Node>
            </Node>
          </Node>
        </State>
      </Pad>
      <Pad Id="MonoDevelop.Debugger.WatchPad">
        <State />
      </Pad>
    </Pads>
  </MonoDevelop.Ide.Workbench>
  <MonoDevelop.Ide.Workspace ActiveConfiguration="Debug" />
  <MonoDevelop.Ide.DebuggingService.PinnedWatches />
</Properties>